trip_planning_agent/__init__.py
trip_planning_agent/utils.py
trip_planning_agent-0.0.1.dist-info/METADATA
trip_planning_agent-0.0.1.dist-info/WHEEL
trip_planning_agent-0.0.1.dist-info/top_level.txt
trip_planning_agent-0.0.1.dist-info/RECORD
