Metadata-Version: 2.2
Name: trip_planning_agent
Version: 0.0.1
Summary: Trip Planning Agent AI Agent Directory to Host All Trip Planning Agent related AI Agents Services, Community, Reviews and More.
Author: AI Agent Hub
Author-email: dingo0927@126.com
Project-URL: homepage, http://www.deepnlp.org/store/ai-agent
Project-URL: repository, https://github.com/AI-Agent-Hub/AI-Agent-Marketplace
Keywords: Trip Planning Agent,AI Agent Marketplace,AI Agent Directory,AI Agents,Agentic AI
Classifier: Development Status :: 3 - Alpha
Classifier: Intended Audience :: Developers
Classifier: Topic :: Software Development :: Build Tools
Classifier: License :: OSI Approved :: MIT License
Requires-Python: >=3.4
Requires-Dist: requests>=2.17.0
Dynamic: author
Dynamic: author-email
Dynamic: classifier
Dynamic: description
Dynamic: description-content-type
Dynamic: keywords
Dynamic: project-url
Dynamic: requires-dist
Dynamic: requires-python
Dynamic: summary
